p1afempy/__init__.py
p1afempy/data_structures.py
p1afempy/indicators.py
p1afempy/io_helpers.py
p1afempy/mesh.py
p1afempy/refinement.py
p1afempy/solvers.py
p1afempy-0.2.15.dist-info/licenses/LICENSE
p1afempy-0.2.15.dist-info/METADATA
p1afempy-0.2.15.dist-info/WHEEL
p1afempy-0.2.15.dist-info/top_level.txt
p1afempy-0.2.15.dist-info/RECORD
