Metadata-Version: 2.4
Name: p1afempy
Version: 0.2.15
Summary: Adaptive P1 FEM algorithms
Author-email: Raphael Leu <raphaelleu95@gmail.com>
Project-URL: Homepage, https://github.com/leuraph/p1afempy
Project-URL: Issues, https://github.com/leuraph/p1afempy/issues
Classifier: Programming Language :: Python :: 3
Classifier: License :: OSI Approved :: MIT License
Classifier: Operating System :: OS Independent
Requires-Python: >=3.9.18
License-File: LICENSE
Requires-Dist: numpy<2.0.0
Requires-Dist: scipy
Requires-Dist: pathlib
Requires-Dist: matplotlib
Requires-Dist: ismember>=1.0.4
Requires-Dist: triangle-cubature
Dynamic: license-file
